media_mgmt_cli/__init__.py
media_mgmt_cli/__main__.py
media_mgmt_cli/aws.py
media_mgmt_cli/cli.py
media_mgmt_cli/config.py
media_mgmt_cli/utils.py
media_mgmt_cli-0.3.3.dist-info/LICENSE
media_mgmt_cli-0.3.3.dist-info/METADATA
media_mgmt_cli-0.3.3.dist-info/WHEEL
media_mgmt_cli-0.3.3.dist-info/entry_points.txt
media_mgmt_cli-0.3.3.dist-info/top_level.txt
media_mgmt_cli-0.3.3.dist-info/RECORD
