Metadata-Version: 2.1
Name: media-mgmt-cli
Version: 0.3.3
Summary: A simple CLI to search and manage media assets in S3 and locally
Home-page: https://github.com/william-cass-wright/media-mgmt-cli
Author: Will Wright
License: Apache License, Version 2.0
Project-URL: Issues, https://github.com/william-cass-wright/media-mgmt-cli/issues
Project-URL: CI, https://github.com/william-cass-wright/media-mgmt-cli/actions
Project-URL: Changelog, https://github.com/william-cass-wright/media-mgmt-cli/releases
Requires-Python: >=3.7
License-File: LICENSE
Requires-Dist: click
Requires-Dist: boto3
Provides-Extra: test
Requires-Dist: pytest ; extra == 'test'
